[
  {
    "id": "nk-airmax-97-black",
    "title": "Nike Air Max 97 Черные",
    "brand": "Nike",
    "season": "all",
    "price": 329, 
    "discount": 10,
    "sizes": [
      { "size": 40, "stock": 2 },
      { "size": 41, "stock": 2 },
      { "size": 42, "stock": 2 },
      { "size": 43, "stock": 2 },
      { "size": 44, "stock": 2 },
      { "size": 45, "stock": 2 }
    ],
    "images": [
      "https://images.unsplash.com/photo-1542291026-7eec264c27ff?w=1200",
      "https://images.unsplash.com/photo-1519741491163-3f2c6f6e4b45?w=1200"
    ],
    "description": "Легендарная волна, комфорт на каждый день.",
    "addedAt": "2025-12-22T12:00:00Z",
    "popularity": 95
  },

  {
    "id": "ad-ultraboost-22-white",
    "title": "Adidas Ultraboost 22 Белые",
    "brand": "Adidas",
    "season": "summer",
    "price": 299,
    "discount": 0,
    "sizes": [
      { "size": 39, "stock": 2 },
      { "size": 40, "stock": 2 },
      { "size": 41, "stock": 2 },
      { "size": 42, "stock": 2 },
      { "size": 43, "stock": 2 },
      { "size": 44, "stock": 2 }
    ],
    "images": [
      "https://images.unsplash.com/photo-1542291026-7eec264c27ff?w=1200",
      "https://images.unsplash.com/photo-1519741491163-3f2c6f6e4b45?w=1200"
    ],
    "description": "Энергия Boost для пробежек и города.",
    "addedAt": "2025-12-23T12:00:00Z",
    "popularity": 88
  },

  {
    "id": "nk-dunk-low-panda",
    "title": "Nike Dunk Low Panda",
    "brand": "Nike",
    "season": "all",
    "price": 279,
    "discount": 5,
    "sizes": [
      { "size": 40, "stock": 2 },
      { "size": 41, "stock": 2 },
      { "size": 42, "stock": 2 },
      { "size": 43, "stock": 2 },
      { "size": 44, "stock": 2 }
    ],
    "images": [
      "https://images.unsplash.com/photo-1542291026-7eec264c27ff?w=1200",
      "https://images.unsplash.com/photo-1519741491163-3f2c6f6e4b45?w=1200"
    ],
    "description": "Классика на каждый день.",
    "addedAt": "2025-12-25T12:00:00Z",
    "popularity": 92
  },

  {
    "id": "nb-990v5-grey",
    "title": "New Balance 990v5 Серые",
    "brand": "New Balance",
    "season": "all",
    "price": 349,
    "discount": 0,
    "sizes": [
      { "size": 40, "stock": 2 },
      { "size": 41, "stock": 2 },
      { "size": 42, "stock": 2 },
      { "size": 43, "stock": 2 },
      { "size": 44, "stock": 2 },
      { "size": 45, "stock": 2 },
      { "size": 46, "stock": 2 }
    ],
    "images": [
      "https://images.unsplash.com/photo-1542291026-7eec264c27ff?w=1200",
      "https://images.unsplash.com/photo-1519741491163-3f2c6f6e4b45?w=1200"
    ],
    "description": "Икона комфорта и качества.",
    "addedAt": "2025-12-24T12:00:00Z",
    "popularity": 85
  },

  {
    "id": "pm-cali-white",
    "title": "Puma Cali Белые",
    "brand": "Puma",
    "season": "summer",
    "price": 219,
    "discount": 15,
    "sizes": [
      { "size": 35, "stock": 2 },
      { "size": 36, "stock": 2 },
      { "size": 37, "stock": 2 },
      { "size": 38, "stock": 2 },
      { "size": 39, "stock": 2 },
      { "size": 40, "stock": 2 }
    ],
    "images": [
      "https://images.unsplash.com/photo-1542291026-7eec264c27ff?w=1200",
      "https://images.unsplash.com/photo-1519741491163-3f2c6f6e4b45?w=1200"
    ],
    "description": "Лёгкие и стильные на лето.",
    "addedAt": "2025-12-26T12:00:00Z",
    "popularity": 78
  },

  {
    "id": "vk-court-black",
    "title": "Vans Old Skool Чёрные",
    "brand": "Vans",
    "season": "all",
    "price": 199,
    "discount": 0,
    "sizes": [
      { "size": 39, "stock": 2 },
      { "size": 40, "stock": 2 },
      { "size": 41, "stock": 2 },
      { "size": 42, "stock": 2 },
      { "size": 43, "stock": 2 },
      { "size": 44, "stock": 2 }
    ],
    "images": [
      "https://images.unsplash.com/photo-1542291026-7eec264c27ff?w=1200",
      "https://images.unsplash.com/photo-1519741491163-3f2c6f6e4b45?w=1200"
    ],
    "description": "Скейт-икона, проверенная временем.",
    "addedAt": "2025-12-27T12:00:00Z",
    "popularity": 80
  },

 {
  "id": "asics-gel-pickax",
  "title": "Asics GEL-PICKAX",
  "brand": "ASICS",
  "season": "all",
  "price": 190,
  "discount": 0,

  "sizes": [
    { "eu": 41, "cm": 25.5 },
    { "eu": 42, "cm": 26.5 },
    { "eu": 43, "cm": 27.3 },
    { "eu": 44, "cm": 27.5 },
    { "eu": 45, "cm": 28.5 }
  ],

  "materials": {
    "upper": "Сетка + синтетические накладки",
    "midsole": "Амортизирующая EVA",
    "outsole": "Резина с трейл‑протектором",
    "lining": "Текстиль"
  },

  "images": [
    "/static/images/asics-gel-pickax-main.jpg",
    "/static/images/asics-gel-pickax-box.jpg",
    "/static/images/asics-gel-pickax-ground.jpg",
    "/static/images/asics-gel-pickax-hand.jpg",
    "/static/images/asics-gel-pickax-sole.jpg"
  ],

  "addedAt": "2026-01-22T12:00:00Z",
  "popularity": 100
}
